[{"id": "Sev:Fatren", "characterId1": "Sev", "characterId2": "Fatren", "type": "", "bookId": "mistborn3"}, {"id": "Druffel:Fatren", "characterId1": "Druffel", "characterId2": "Fatren", "type": "", "bookId": "mistborn3"}, {"id": "Elend_Venture:Fatren", "characterId1": "Elend_Venture", "characterId2": "Fatren", "type": "", "bookId": "mistborn3"}, {"id": "Vin:Elend_Venture", "characterId1": "Vin", "characterId2": "Elend_Venture", "type": "", "bookId": "mistborn3"}, {"id": "Sazed:Edgard_Ladrian", "characterId1": "Sazed", "characterId2": "Edgard_Ladrian", "type": "", "bookId": "mistborn3"}, {"id": "Sazed:Elend_Venture", "characterId1": "Sazed", "characterId2": "Elend_Venture", "type": "", "bookId": "mistborn3"}, {"id": "Sazed:Marsh", "characterId1": "Sazed", "characterId2": "Marsh", "type": "", "bookId": "mistborn3"}, {"id": "Sazed:Vin", "characterId1": "Sazed", "characterId2": "Vin", "type": "", "bookId": "mistborn3"}, {"id": "Elend_Venture:Vin", "characterId1": "Elend_Venture", "characterId2": "Vin", "type": "", "bookId": "mistborn3"}, {"id": "Elend_Venture:Fatren", "characterId1": "Elend_Venture", "characterId2": "Fatren", "type": "", "bookId": "mistborn3"}, {"id": "Vin:Fatren", "characterId1": "Vin", "characterId2": "Fatren", "type": "", "bookId": "mistborn3"}, {"id": "Vin:Fatren", "characterId1": "Vin", "characterId2": "Fatren", "type": "", "bookId": "mistborn3"}, {"id": "Vin:Kelsier", "characterId1": "Vin", "characterId2": "Kelsier", "type": "", "bookId": "mistborn3"}, {"id": "Vin:Elend_Venture", "characterId1": "Vin", "characterId2": "Elend_Venture", "type": "", "bookId": "mistborn3"}, {"id": "Kelsier:Elend_Venture", "characterId1": "Kelsier", "characterId2": "Elend_Venture", "type": "", "bookId": "mistborn3"}, {"id": "Sazed:Kwaan", "characterId1": "Sazed", "characterId2": "Kwaan", "type": "", "bookId": "mistborn3"}, {"id": "VarSell:TenSoon", "characterId1": "VarSell", "characterId2": "TenSoon", "type": "", "bookId": "mistborn3"}, {"id": "Demoux:Fatren", "characterId1": "Demoux", "characterId2": "Fatren", "type": "", "bookId": "mistborn3"}, {"id": "Demoux:Elend_Venture", "characterId1": "Demoux", "characterId2": "Elend_Venture", "type": "", "bookId": "mistborn3"}, {"id": "Sazed:Demoux", "characterId1": "Sazed", "characterId2": "Demoux", "type": "", "bookId": "mistborn3"}, {"id": "Sazed:Edgard_Ladrian", "characterId1": "Sazed", "characterId2": "Edgard_Ladrian", "type": "", "bookId": "mistborn3"}, {"id": "Demoux:Edgard_Ladrian", "characterId1": "Demoux", "characterId2": "Edgard_Ladrian", "type": "", "bookId": "mistborn3"}, {"id": "Cett_(coach_owner):Demoux", "characterId1": "Cett_(coach_owner)", "characterId2": "Demoux", "type": "", "bookId": "mistborn3"}, {"id": "Vin:Demoux", "characterId1": "Vin", "characterId2": "Demoux", "type": "", "bookId": "mistborn3"}, {"id": "Hammond:Elend_Venture", "characterId1": "Hammond", "characterId2": "Elend_Venture", "type": "", "bookId": "mistborn3"}, {"id": "Rashek:Elend_Venture", "characterId1": "Rashek", "characterId2": "Elend_Venture", "type": "", "bookId": "mistborn3"}, {"id": "Mare:Kelsier", "characterId1": "Mare", "characterId2": "Kelsier", "type": "", "bookId": "mistborn3"}, {"id": "Sazed:Edgard_Ladrian", "characterId1": "Sazed", "characterId2": "Edgard_Ladrian", "type": "", "bookId": "mistborn3"}, {"id": "Sazed:Kelsier", "characterId1": "Sazed", "characterId2": "Kelsier", "type": "", "bookId": "mistborn3"}, {"id": "Edgard_Ladrian:Kelsier", "characterId1": "Edgard_Ladrian", "characterId2": "Kelsier", "type": "", "bookId": "mistborn3"}, {"id": "Sazed:Goradel", "characterId1": "Sazed", "characterId2": "Goradel", "type": "", "bookId": "mistborn3"}, {"id": "Edgard_Ladrian:Allrianne_Cett", "characterId1": "Edgard_Ladrian", "characterId2": "Allrianne_Cett", "type": "", "bookId": "mistborn3"}, {"id": "Sazed:Allrianne_Cett", "characterId1": "Sazed", "characterId2": "Allrianne_Cett", "type": "", "bookId": "mistborn3"}, {"id": "Edgard_Ladrian:Goradel", "characterId1": "Edgard_Ladrian", "characterId2": "Goradel", "type": "", "bookId": "mistborn3"}, {"id": "Sazed:Vin", "characterId1": "Sazed", "characterId2": "Vin", "type": "", "bookId": "mistborn3"}, {"id": "Sazed:Demoux", "characterId1": "Sazed", "characterId2": "Demoux", "type": "", "bookId": "mistborn3"}, {"id": "Vin:Demoux", "characterId1": "Vin", "characterId2": "Demoux", "type": "", "bookId": "mistborn3"}, {"id": "Vin:Kelsier", "characterId1": "Vin", "characterId2": "Kelsier", "type": "", "bookId": "mistborn3"}, {"id": "TenSoon:Vin", "characterId1": "TenSoon", "characterId2": "Vin", "type": "", "bookId": "mistborn3"}, {"id": "TenSoon:Zane_Venture", "characterId1": "TenSoon", "characterId2": "Zane_Venture", "type": "", "bookId": "mistborn3"}, {"id": "Vin:Zane_Venture", "characterId1": "Vin", "characterId2": "Zane_Venture", "type": "", "bookId": "mistborn3"}, {"id": "KanPaar:Zane_Venture", "characterId1": "KanPaar", "characterId2": "Zane_Venture", "type": "", "bookId": "mistborn3"}, {"id": "KanPaar:TenSoon", "characterId1": "KanPaar", "characterId2": "TenSoon", "type": "", "bookId": "mistborn3"}, {"id": "Vin:Zane_Venture", "characterId1": "Vin", "characterId2": "Zane_Venture", "type": "", "bookId": "mistborn3"}, {"id": "Cladent:Dockson", "characterId1": "Cladent", "characterId2": "Dockson", "type": "", "bookId": "mistborn3"}, {"id": "Edgard_Ladrian:Elend_Venture", "characterId1": "Edgard_Ladrian", "characterId2": "Elend_Venture", "type": "", "bookId": "mistborn3"}, {"id": "Cett_(coach_owner):Elend_Venture", "characterId1": "Cett_(coach_owner)", "characterId2": "Elend_Venture", "type": "", "bookId": "mistborn3"}, {"id": "Cett_(coach_owner):Allrianne_Cett", "characterId1": "Cett_(coach_owner)", "characterId2": "Allrianne_Cett", "type": "", "bookId": "mistborn3"}, {"id": "Cett_(coach_owner):Edgard_Ladrian", "characterId1": "Cett_(coach_owner)", "characterId2": "Edgard_Ladrian", "type": "", "bookId": "mistborn3"}, {"id": "Vin:Reen", "characterId1": "Vin", "characterId2": "Reen", "type": "", "bookId": "mistborn3"}, {"id": "Hammond:El", "characterId1": "Hammond", "characterId2": "El", "type": "", "bookId": "mistborn3"}, {"id": "Cett_(coach_owner):Demoux", "characterId1": "Cett_(coach_owner)", "characterId2": "Demoux", "type": "", "bookId": "mistborn3"}, {"id": "Cett_(coach_owner):Edgard_Ladrian", "characterId1": "Cett_(coach_owner)", "characterId2": "Edgard_Ladrian", "type": "", "bookId": "mistborn3"}, {"id": "Demoux:Edgard_Ladrian", "characterId1": "Demoux", "characterId2": "Edgard_Ladrian", "type": "", "bookId": "mistborn3"}, {"id": "Cett_(coach_owner):Gneorndin_Cett", "characterId1": "Cett_(coach_owner)", "characterId2": "Gneorndin_Cett", "type": "", "bookId": "mistborn3"}, {"id": "Hammond:Sazed", "characterId1": "Hammond", "characterId2": "Sazed", "type": "", "bookId": "mistborn3"}, {"id": "Hammond:Edgard_Ladrian", "characterId1": "Hammond", "characterId2": "Edgard_Ladrian", "type": "", "bookId": "mistborn3"}, {"id": "Hammond:Cett_(coach_owner)", "characterId1": "Hammond", "characterId2": "Cett_(coach_owner)", "type": "", "bookId": "mistborn3"}, {"id": "Hammond:Elend_Venture", "characterId1": "Hammond", "characterId2": "Elend_Venture", "type": "", "bookId": "mistborn3"}, {"id": "Cett_(coach_owner):Elend_Venture", "characterId1": "Cett_(coach_owner)", "characterId2": "Elend_Venture", "type": "", "bookId": "mistborn3"}, {"id": "Janarle:Elend_Venture", "characterId1": "Janarle", "characterId2": "Elend_Venture", "type": "", "bookId": "mistborn3"}, {"id": "Straff_Venture:Janarle", "characterId1": "Straff_Venture", "characterId2": "Janarle", "type": "", "bookId": "mistborn3"}, {"id": "Straff_Venture:Elend_Venture", "characterId1": "Straff_Venture", "characterId2": "Elend_Venture", "type": "", "bookId": "mistborn3"}, {"id": "Janarle:Elend_Venture", "characterId1": "Janarle", "characterId2": "Elend_Venture", "type": "", "bookId": "mistborn3"}, {"id": "Cett_(coach_owner):Janarle", "characterId1": "Cett_(coach_owner)", "characterId2": "Janarle", "type": "", "bookId": "mistborn3"}, {"id": "Cladent:Cett_(coach_owner)", "characterId1": "Cladent", "characterId2": "Cett_(coach_owner)", "type": "", "bookId": "mistborn3"}, {"id": "Demoux:Edgard_Ladrian", "characterId1": "Demoux", "characterId2": "Edgard_Ladrian", "type": "", "bookId": "mistborn3"}, {"id": "Kelsier:Edgard_Ladrian", "characterId1": "Kelsier", "characterId2": "Edgard_Ladrian", "type": "", "bookId": "mistborn3"}, {"id": "Sazed:Edgard_Ladrian", "characterId1": "Sazed", "characterId2": "Edgard_Ladrian", "type": "", "bookId": "mistborn3"}, {"id": "Sazed:Allrianne_Cett", "characterId1": "Sazed", "characterId2": "Allrianne_Cett", "type": "", "bookId": "mistborn3"}, {"id": "Edgard_Ladrian:Allrianne_Cett", "characterId1": "Edgard_Ladrian", "characterId2": "Allrianne_Cett", "type": "", "bookId": "mistborn3"}, {"id": "Ati:Marsh", "characterId1": "Ati", "characterId2": "Marsh", "type": "", "bookId": "mistborn3"}, {"id": "Mare:Kelsier", "characterId1": "Mare", "characterId2": "Kelsier", "type": "", "bookId": "mistborn3"}, {"id": "Mare:Marsh", "characterId1": "Mare", "characterId2": "Marsh", "type": "", "bookId": "mistborn3"}, {"id": "Kelsier:Marsh", "characterId1": "Kelsier", "characterId2": "Marsh", "type": "", "bookId": "mistborn3"}, {"id": "Kelsier:Marsh", "characterId1": "Kelsier", "characterId2": "Marsh", "type": "", "bookId": "mistborn3"}, {"id": "Cladent:Kelsier", "characterId1": "Cladent", "characterId2": "Kelsier", "type": "", "bookId": "mistborn3"}, {"id": "Cladent:Spook", "characterId1": "Cladent", "characterId2": "Spook", "type": "", "bookId": "mistborn3"}, {"id": "Kelsier:Spook", "characterId1": "Kelsier", "characterId2": "Spook", "type": "", "bookId": "mistborn3"}, {"id": "Vin:Elend_Venture", "characterId1": "Vin", "characterId2": "Elend_Venture", "type": "", "bookId": "mistborn3"}, {"id": "Vin:Spook", "characterId1": "Vin", "characterId2": "Spook", "type": "", "bookId": "mistborn3"}, {"id": "Elend_Venture:Spook", "characterId1": "Elend_Venture", "characterId2": "Spook", "type": "", "bookId": "mistborn3"}, {"id": "Elend_Venture:Spook", "characterId1": "Elend_Venture", "characterId2": "Spook", "type": "", "bookId": "mistborn3"}, {"id": "Olid:Quellion", "characterId1": "Olid", "characterId2": "Quellion", "type": "", "bookId": "mistborn3"}, {"id": "Kelsier:Spook", "characterId1": "Kelsier", "characterId2": "Spook", "type": "", "bookId": "mistborn3"}, {"id": "Hammond:Vin", "characterId1": "Hammond", "characterId2": "Vin", "type": "", "bookId": "mistborn3"}, {"id": "Hammond:Elend_Venture", "characterId1": "Hammond", "characterId2": "Elend_Venture", "type": "", "bookId": "mistborn3"}, {"id": "Vin:Elend_Venture", "characterId1": "Vin", "characterId2": "Elend_Venture", "type": "", "bookId": "mistborn3"}, {"id": "Hammond:Vin", "characterId1": "Hammond", "characterId2": "Vin", "type": "", "bookId": "mistborn3"}, {"id": "Hammond:Dockson", "characterId1": "Hammond", "characterId2": "Dockson", "type": "", "bookId": "mistborn3"}, {"id": "Hammond:Edgard_Ladrian", "characterId1": "Hammond", "characterId2": "Edgard_Ladrian", "type": "", "bookId": "mistborn3"}, {"id": "Dockson:Edgard_Ladrian", "characterId1": "Dockson", "characterId2": "Edgard_Ladrian", "type": "", "bookId": "mistborn3"}, {"id": "Durn:Spook", "characterId1": "Durn", "characterId2": "Spook", "type": "", "bookId": "mistborn3"}, {"id": "Durn:Spook", "characterId1": "Durn", "characterId2": "Spook", "type": "", "bookId": "mistborn3"}, {"id": "Durn:Beldre", "characterId1": "Durn", "characterId2": "Beldre", "type": "", "bookId": "mistborn3"}, {"id": "Spook:Beldre", "characterId1": "Spook", "characterId2": "Beldre", "type": "", "bookId": "mistborn3"}, {"id": "Durn:Kelsier", "characterId1": "Durn", "characterId2": "Kelsier", "type": "", "bookId": "mistborn3"}, {"id": "Vin:Spook", "characterId1": "Vin", "characterId2": "Spook", "type": "", "bookId": "mistborn3"}, {"id": "Spook:Beldre", "characterId1": "Spook", "characterId2": "Beldre", "type": "", "bookId": "mistborn3"}, {"id": "Hammond:Vin", "characterId1": "Hammond", "characterId2": "Vin", "type": "", "bookId": "mistborn3"}, {"id": "Hammond:Kelsier", "characterId1": "Hammond", "characterId2": "Kelsier", "type": "", "bookId": "mistborn3"}, {"id": "Vin:Kelsier", "characterId1": "Vin", "characterId2": "Kelsier", "type": "", "bookId": "mistborn3"}, {"id": "Quellion:Spook", "characterId1": "Quellion", "characterId2": "Spook", "type": "", "bookId": "mistborn3"}, {"id": "Demoux:Kelsier", "characterId1": "Demoux", "characterId2": "Kelsier", "type": "", "bookId": "mistborn3"}, {"id": "MeLaan:TenSoon", "characterId1": "MeLaan", "characterId2": "TenSoon", "type": "", "bookId": "mistborn3"}, {"id": "Ati:MeLaan", "characterId1": "Ati", "characterId2": "MeLaan", "type": "", "bookId": "mistborn3"}, {"id": "TenSoon:Zane_Venture", "characterId1": "TenSoon", "characterId2": "Zane_Venture", "type": "", "bookId": "mistborn3"}, {"id": "Rashek:Alendi", "characterId1": "Rashek", "characterId2": "Alendi", "type": "", "bookId": "mistborn3"}, {"id": "Vin:Alendi", "characterId1": "Vin", "characterId2": "Alendi", "type": "", "bookId": "mistborn3"}, {"id": "Sazed:TenSoon", "characterId1": "Sazed", "characterId2": "TenSoon", "type": "", "bookId": "mistborn3"}, {"id": "Sazed:Elend_Venture", "characterId1": "Sazed", "characterId2": "Elend_Venture", "type": "", "bookId": "mistborn3"}, {"id": "TenSoon:Elend_Venture", "characterId1": "TenSoon", "characterId2": "Elend_Venture", "type": "", "bookId": "mistborn3"}, {"id": "Sazed:Ati", "characterId1": "Sazed", "characterId2": "Ati", "type": "", "bookId": "mistborn3"}, {"id": "Vin:Ati", "characterId1": "Vin", "characterId2": "Ati", "type": "", "bookId": "mistborn3"}, {"id": "Noorden:Elend_Venture", "characterId1": "Noorden", "characterId2": "Elend_Venture", "type": "", "bookId": "mistborn3"}, {"id": "Noorden:Vin", "characterId1": "Noorden", "characterId2": "Vin", "type": "", "bookId": "mistborn3"}, {"id": "Sazed:Edgard_Ladrian", "characterId1": "Sazed", "characterId2": "Edgard_Ladrian", "type": "", "bookId": "mistborn3"}, {"id": "Sazed:Goradel", "characterId1": "Sazed", "characterId2": "Goradel", "type": "", "bookId": "mistborn3"}, {"id": "Edgard_Ladrian:Goradel", "characterId1": "Edgard_Ladrian", "characterId2": "Goradel", "type": "", "bookId": "mistborn3"}, {"id": "Sazed:Vedlew", "characterId1": "Sazed", "characterId2": "Vedlew", "type": "", "bookId": "mistborn3"}, {"id": "Margel:Spook", "characterId1": "Margel", "characterId2": "Spook", "type": "", "bookId": "mistborn3"}, {"id": "Ati:Kelsier", "characterId1": "Ati", "characterId2": "Kelsier", "type": "", "bookId": "mistborn3"}, {"id": "Hammond:Vin", "characterId1": "Hammond", "characterId2": "Vin", "type": "", "bookId": "mistborn3"}, {"id": "Hammond:Cett_(coach_owner)", "characterId1": "Hammond", "characterId2": "Cett_(coach_owner)", "type": "", "bookId": "mistborn3"}, {"id": "Hammond:Demoux", "characterId1": "Hammond", "characterId2": "Demoux", "type": "", "bookId": "mistborn3"}, {"id": "Vin:Cett_(coach_owner)", "characterId1": "Vin", "characterId2": "Cett_(coach_owner)", "type": "", "bookId": "mistborn3"}, {"id": "Vin:Demoux", "characterId1": "Vin", "characterId2": "Demoux", "type": "", "bookId": "mistborn3"}, {"id": "Cett_(coach_owner):Demoux", "characterId1": "Cett_(coach_owner)", "characterId2": "Demoux", "type": "", "bookId": "mistborn3"}, {"id": "Felt:Spook", "characterId1": "Felt", "characterId2": "Spook", "type": "", "bookId": "mistborn3"}, {"id": "Hammond:Cett_(coach_owner)", "characterId1": "Hammond", "characterId2": "Cett_(coach_owner)", "type": "", "bookId": "mistborn3"}, {"id": "Hammond:Demoux", "characterId1": "Hammond", "characterId2": "Demoux", "type": "", "bookId": "mistborn3"}, {"id": "Cladent:Kelsier", "characterId1": "Cladent", "characterId2": "Kelsier", "type": "", "bookId": "mistborn3"}, {"id": "Hammond:Vin", "characterId1": "Hammond", "characterId2": "Vin", "type": "", "bookId": "mistborn3"}, {"id": "Hammond:Demoux", "characterId1": "Hammond", "characterId2": "Demoux", "type": "", "bookId": "mistborn3"}, {"id": "Vin:Demoux", "characterId1": "Vin", "characterId2": "Demoux", "type": "", "bookId": "mistborn3"}, {"id": "Vin:Cett_(coach_owner)", "characterId1": "Vin", "characterId2": "Cett_(coach_owner)", "type": "", "bookId": "mistborn3"}, {"id": "Cett_(coach_owner):Slowswift", "characterId1": "Cett_(coach_owner)", "characterId2": "Slowswift", "type": "", "bookId": "mistborn3"}, {"id": "Cett_(coach_owner):Hoid", "characterId1": "Cett_(coach_owner)", "characterId2": "Hoid", "type": "", "bookId": "mistborn3"}, {"id": "Vin:Slowswift", "characterId1": "Vin", "characterId2": "Slowswift", "type": "", "bookId": "mistborn3"}, {"id": "Jastes_Lekal:Elend_Venture", "characterId1": "Jastes_Lekal", "characterId2": "Elend_Venture", "type": "", "bookId": "mistborn3"}, {"id": "Sazed:Edgard_Ladrian", "characterId1": "Sazed", "characterId2": "Edgard_Ladrian", "type": "", "bookId": "mistborn3"}, {"id": "Sazed:Goradel", "characterId1": "Sazed", "characterId2": "Goradel", "type": "", "bookId": "mistborn3"}, {"id": "Sazed:Allrianne_Cett", "characterId1": "Sazed", "characterId2": "Allrianne_Cett", "type": "", "bookId": "mistborn3"}, {"id": "Edgard_Ladrian:Goradel", "characterId1": "Edgard_Ladrian", "characterId2": "Goradel", "type": "", "bookId": "mistborn3"}, {"id": "Edgard_Ladrian:Allrianne_Cett", "characterId1": "Edgard_Ladrian", "characterId2": "Allrianne_Cett", "type": "", "bookId": "mistborn3"}, {"id": "Goradel:Allrianne_Cett", "characterId1": "Goradel", "characterId2": "Allrianne_Cett", "type": "", "bookId": "mistborn3"}, {"id": "Sazed:Quellion", "characterId1": "Sazed", "characterId2": "Quellion", "type": "", "bookId": "mistborn3"}, {"id": "Sazed:Elend_Venture", "characterId1": "Sazed", "characterId2": "Elend_Venture", "type": "", "bookId": "mistborn3"}, {"id": "Quellion:Elend_Venture", "characterId1": "Quellion", "characterId2": "Elend_Venture", "type": "", "bookId": "mistborn3"}, {"id": "Straff_Venture:Ashweather_Cett", "characterId1": "Straff_Venture", "characterId2": "Ashweather_Cett", "type": "", "bookId": "mistborn3"}, {"id": "Sazed:Kelsier", "characterId1": "Sazed", "characterId2": "Kelsier", "type": "", "bookId": "mistborn3"}, {"id": "Sazed:Quellion", "characterId1": "Sazed", "characterId2": "Quellion", "type": "", "bookId": "mistborn3"}, {"id": "Quellion:Edgard_Ladrian", "characterId1": "Quellion", "characterId2": "Edgard_Ladrian", "type": "", "bookId": "mistborn3"}, {"id": "Edgard_Ladrian:Spook", "characterId1": "Edgard_Ladrian", "characterId2": "Spook", "type": "", "bookId": "mistborn3"}, {"id": "Sazed:Spook", "characterId1": "Sazed", "characterId2": "Spook", "type": "", "bookId": "mistborn3"}, {"id": "Sazed:Edgard_Ladrian", "characterId1": "Sazed", "characterId2": "Edgard_Ladrian", "type": "", "bookId": "mistborn3"}, {"id": "Sazed:Spook", "characterId1": "Sazed", "characterId2": "Spook", "type": "", "bookId": "mistborn3"}, {"id": "Edgard_Ladrian:Spook", "characterId1": "Edgard_Ladrian", "characterId2": "Spook", "type": "", "bookId": "mistborn3"}, {"id": "Edgard_Ladrian:Spook", "characterId1": "Edgard_Ladrian", "characterId2": "Spook", "type": "", "bookId": "mistborn3"}, {"id": "Edgard_Ladrian:Allrianne_Cett", "characterId1": "Edgard_Ladrian", "characterId2": "Allrianne_Cett", "type": "", "bookId": "mistborn3"}, {"id": "Spook:Allrianne_Cett", "characterId1": "Spook", "characterId2": "Allrianne_Cett", "type": "", "bookId": "mistborn3"}, {"id": "Hammond:Cett_(coach_owner)", "characterId1": "Hammond", "characterId2": "Cett_(coach_owner)", "type": "", "bookId": "mistborn3"}, {"id": "Hammond:Edgard_Ladrian", "characterId1": "Hammond", "characterId2": "Edgard_Ladrian", "type": "", "bookId": "mistborn3"}, {"id": "Cett_(coach_owner):Edgard_Ladrian", "characterId1": "Cett_(coach_owner)", "characterId2": "Edgard_Ladrian", "type": "", "bookId": "mistborn3"}, {"id": "Sazed:Vin", "characterId1": "Sazed", "characterId2": "Vin", "type": "", "bookId": "mistborn3"}, {"id": "Sazed:Cett_(coach_owner)", "characterId1": "Sazed", "characterId2": "Cett_(coach_owner)", "type": "", "bookId": "mistborn3"}, {"id": "Vin:Cett_(coach_owner)", "characterId1": "Vin", "characterId2": "Cett_(coach_owner)", "type": "", "bookId": "mistborn3"}, {"id": "Sazed:Cett_(coach_owner)", "characterId1": "Sazed", "characterId2": "Cett_(coach_owner)", "type": "", "bookId": "mistborn3"}, {"id": "Hammond:Kelsier", "characterId1": "Hammond", "characterId2": "Kelsier", "type": "", "bookId": "mistborn3"}, {"id": "Elend_Venture:Tindwyl_Ladrian", "characterId1": "Elend_Venture", "characterId2": "Tindwyl_Ladrian", "type": "", "bookId": "mistborn3"}, {"id": "Aradan_Yomen:Vin", "characterId1": "Aradan_Yomen", "characterId2": "Vin", "type": "", "bookId": "mistborn3"}, {"id": "Aradan_Yomen:Elend_Venture", "characterId1": "Aradan_Yomen", "characterId2": "Elend_Venture", "type": "", "bookId": "mistborn3"}, {"id": "Vin:Elend_Venture", "characterId1": "Vin", "characterId2": "Elend_Venture", "type": "", "bookId": "mistborn3"}, {"id": "Sazed:Edgard_Ladrian", "characterId1": "Sazed", "characterId2": "Edgard_Ladrian", "type": "", "bookId": "mistborn3"}, {"id": "Sazed:Spook", "characterId1": "Sazed", "characterId2": "Spook", "type": "", "bookId": "mistborn3"}, {"id": "Sazed:Allrianne_Cett", "characterId1": "Sazed", "characterId2": "Allrianne_Cett", "type": "", "bookId": "mistborn3"}, {"id": "Edgard_Ladrian:Spook", "characterId1": "Edgard_Ladrian", "characterId2": "Spook", "type": "", "bookId": "mistborn3"}, {"id": "Edgard_Ladrian:Allrianne_Cett", "characterId1": "Edgard_Ladrian", "characterId2": "Allrianne_Cett", "type": "", "bookId": "mistborn3"}, {"id": "Spook:Allrianne_Cett", "characterId1": "Spook", "characterId2": "Allrianne_Cett", "type": "", "bookId": "mistborn3"}, {"id": "Telden_Hasting:Elend_Venture", "characterId1": "Telden_Hasting", "characterId2": "Elend_Venture", "type": "", "bookId": "mistborn3"}, {"id": "Telden_Hasting:El", "characterId1": "Telden_Hasting", "characterId2": "El", "type": "", "bookId": "mistborn3"}, {"id": "Telden_Hasting:Elend_Venture", "characterId1": "Telden_Hasting", "characterId2": "Elend_Venture", "type": "", "bookId": "mistborn3"}, {"id": "El:Elend_Venture", "characterId1": "El", "characterId2": "Elend_Venture", "type": "", "bookId": "mistborn3"}, {"id": "Telden_Hasting:El", "characterId1": "Telden_Hasting", "characterId2": "El", "type": "", "bookId": "mistborn3"}, {"id": "Vin:Edgard_Ladrian", "characterId1": "Vin", "characterId2": "Edgard_Ladrian", "type": "", "bookId": "mistborn3"}, {"id": "Telden_Hasting:Vin", "characterId1": "Telden_Hasting", "characterId2": "Vin", "type": "", "bookId": "mistborn3"}, {"id": "Telden_Hasting:Elend_Venture", "characterId1": "Telden_Hasting", "characterId2": "Elend_Venture", "type": "", "bookId": "mistborn3"}, {"id": "Vin:Elend_Venture", "characterId1": "Vin", "characterId2": "Elend_Venture", "type": "", "bookId": "mistborn3"}, {"id": "Urdree:Elend_Venture", "characterId1": "Urdree", "characterId2": "Elend_Venture", "type": "", "bookId": "mistborn3"}, {"id": "Durn:Edgard_Ladrian", "characterId1": "Durn", "characterId2": "Edgard_Ladrian", "type": "", "bookId": "mistborn3"}, {"id": "Durn:Spook", "characterId1": "Durn", "characterId2": "Spook", "type": "", "bookId": "mistborn3"}, {"id": "Edgard_Ladrian:Spook", "characterId1": "Edgard_Ladrian", "characterId2": "Spook", "type": "", "bookId": "mistborn3"}, {"id": "Quellion:Kelsier", "characterId1": "Quellion", "characterId2": "Kelsier", "type": "", "bookId": "mistborn3"}, {"id": "Mailey:Durn", "characterId1": "Mailey", "characterId2": "Durn", "type": "", "bookId": "mistborn3"}, {"id": "Hammond:Cett_(coach_owner)", "characterId1": "Hammond", "characterId2": "Cett_(coach_owner)", "type": "", "bookId": "mistborn3"}, {"id": "Hammond:Demoux", "characterId1": "Hammond", "characterId2": "Demoux", "type": "", "bookId": "mistborn3"}, {"id": "Cett_(coach_owner):Demoux", "characterId1": "Cett_(coach_owner)", "characterId2": "Demoux", "type": "", "bookId": "mistborn3"}, {"id": "Cett_(coach_owner):Tindwyl_Ladrian", "characterId1": "Cett_(coach_owner)", "characterId2": "Tindwyl_Ladrian", "type": "", "bookId": "mistborn3"}, {"id": "Kelsier:Elend_Venture", "characterId1": "Kelsier", "characterId2": "Elend_Venture", "type": "", "bookId": "mistborn3"}, {"id": "Franson:Spook", "characterId1": "Franson", "characterId2": "Spook", "type": "", "bookId": "mistborn3"}, {"id": "Hammond:Cett_(coach_owner)", "characterId1": "Hammond", "characterId2": "Cett_(coach_owner)", "type": "", "bookId": "mistborn3"}, {"id": "Hammond:Elend_Venture", "characterId1": "Hammond", "characterId2": "Elend_Venture", "type": "", "bookId": "mistborn3"}, {"id": "Hammond:Demoux", "characterId1": "Hammond", "characterId2": "Demoux", "type": "", "bookId": "mistborn3"}, {"id": "Hammond:Noorden", "characterId1": "Hammond", "characterId2": "Noorden", "type": "", "bookId": "mistborn3"}, {"id": "Cett_(coach_owner):Elend_Venture", "characterId1": "Cett_(coach_owner)", "characterId2": "Elend_Venture", "type": "", "bookId": "mistborn3"}, {"id": "Cett_(coach_owner):Demoux", "characterId1": "Cett_(coach_owner)", "characterId2": "Demoux", "type": "", "bookId": "mistborn3"}, {"id": "Cett_(coach_owner):Noorden", "characterId1": "Cett_(coach_owner)", "characterId2": "Noorden", "type": "", "bookId": "mistborn3"}, {"id": "Elend_Venture:Demoux", "characterId1": "Elend_Venture", "characterId2": "Demoux", "type": "", "bookId": "mistborn3"}, {"id": "Elend_Venture:Noorden", "characterId1": "Elend_Venture", "characterId2": "Noorden", "type": "", "bookId": "mistborn3"}, {"id": "Demoux:Noorden", "characterId1": "Demoux", "characterId2": "Noorden", "type": "", "bookId": "mistborn3"}, {"id": "Hammond:Marsh", "characterId1": "Hammond", "characterId2": "Marsh", "type": "", "bookId": "mistborn3"}, {"id": "Vin:Marsh", "characterId1": "Vin", "characterId2": "Marsh", "type": "", "bookId": "mistborn3"}, {"id": "Vin:Demoux", "characterId1": "Vin", "characterId2": "Demoux", "type": "", "bookId": "mistborn3"}, {"id": "Vin:Elend_Venture", "characterId1": "Vin", "characterId2": "Elend_Venture", "type": "", "bookId": "mistborn3"}, {"id": "Demoux:Elend_Venture", "characterId1": "Demoux", "characterId2": "Elend_Venture", "type": "", "bookId": "mistborn3"}, {"id": "Hammond:Noorden", "characterId1": "Hammond", "characterId2": "Noorden", "type": "", "bookId": "mistborn3"}, {"id": "Hammond:Cett_(coach_owner)", "characterId1": "Hammond", "characterId2": "Cett_(coach_owner)", "type": "", "bookId": "mistborn3"}, {"id": "Noorden:Cett_(coach_owner)", "characterId1": "Noorden", "characterId2": "Cett_(coach_owner)", "type": "", "bookId": "mistborn3"}, {"id": "Conrad:Demoux", "characterId1": "Conrad", "characterId2": "Demoux", "type": "", "bookId": "mistborn3"}, {"id": "Sazed:Quellion", "characterId1": "Sazed", "characterId2": "Quellion", "type": "", "bookId": "mistborn3"}, {"id": "Sazed:Spook", "characterId1": "Sazed", "characterId2": "Spook", "type": "", "bookId": "mistborn3"}, {"id": "Quellion:Spook", "characterId1": "Quellion", "characterId2": "Spook", "type": "", "bookId": "mistborn3"}, {"id": "Elend_Venture:Reen", "characterId1": "Elend_Venture", "characterId2": "Reen", "type": "", "bookId": "mistborn3"}, {"id": "Edgard_Ladrian:Reen", "characterId1": "Edgard_Ladrian", "characterId2": "Reen", "type": "", "bookId": "mistborn3"}, {"id": "Quellion:Spook", "characterId1": "Quellion", "characterId2": "Spook", "type": "", "bookId": "mistborn3"}, {"id": "Quellion:Beldre", "characterId1": "Quellion", "characterId2": "Beldre", "type": "", "bookId": "mistborn3"}, {"id": "Spook:Beldre", "characterId1": "Spook", "characterId2": "Beldre", "type": "", "bookId": "mistborn3"}, {"id": "Hammond:Demoux", "characterId1": "Hammond", "characterId2": "Demoux", "type": "", "bookId": "mistborn3"}, {"id": "Hammond:Elend_Venture", "characterId1": "Hammond", "characterId2": "Elend_Venture", "type": "", "bookId": "mistborn3"}, {"id": "Demoux:Elend_Venture", "characterId1": "Demoux", "characterId2": "Elend_Venture", "type": "", "bookId": "mistborn3"}, {"id": "Hammond:Noorden", "characterId1": "Hammond", "characterId2": "Noorden", "type": "", "bookId": "mistborn3"}, {"id": "Ati:Reen", "characterId1": "Ati", "characterId2": "Reen", "type": "", "bookId": "mistborn3"}, {"id": "Vin:Ati", "characterId1": "Vin", "characterId2": "Ati", "type": "", "bookId": "mistborn3"}, {"id": "Vin:Reen", "characterId1": "Vin", "characterId2": "Reen", "type": "", "bookId": "mistborn3"}, {"id": "Ati:Reen", "characterId1": "Ati", "characterId2": "Reen", "type": "", "bookId": "mistborn3"}, {"id": "Ati:Zane_Venture", "characterId1": "Ati", "characterId2": "Zane_Venture", "type": "", "bookId": "mistborn3"}, {"id": "Vin:Ati", "characterId1": "Vin", "characterId2": "Ati", "type": "", "bookId": "mistborn3"}, {"id": "Vin:Rashek", "characterId1": "Vin", "characterId2": "Rashek", "type": "", "bookId": "mistborn3"}, {"id": "Vin:Alendi", "characterId1": "Vin", "characterId2": "Alendi", "type": "", "bookId": "mistborn3"}, {"id": "Ati:Rashek", "characterId1": "Ati", "characterId2": "Rashek", "type": "", "bookId": "mistborn3"}, {"id": "Ati:Alendi", "characterId1": "Ati", "characterId2": "Alendi", "type": "", "bookId": "mistborn3"}, {"id": "Rashek:Alendi", "characterId1": "Rashek", "characterId2": "Alendi", "type": "", "bookId": "mistborn3"}, {"id": "Ati:Alendi", "characterId1": "Ati", "characterId2": "Alendi", "type": "", "bookId": "mistborn3"}, {"id": "Goradel:Spook", "characterId1": "Goradel", "characterId2": "Spook", "type": "", "bookId": "mistborn3"}, {"id": "Edgard_Ladrian:Spook", "characterId1": "Edgard_Ladrian", "characterId2": "Spook", "type": "", "bookId": "mistborn3"}, {"id": "Edgard_Ladrian:Beldre", "characterId1": "Edgard_Ladrian", "characterId2": "Beldre", "type": "", "bookId": "mistborn3"}, {"id": "Spook:Beldre", "characterId1": "Spook", "characterId2": "Beldre", "type": "", "bookId": "mistborn3"}, {"id": "Telden_Hasting:Vin", "characterId1": "Telden_Hasting", "characterId2": "Vin", "type": "", "bookId": "mistborn3"}, {"id": "Vin:TenSoon", "characterId1": "Vin", "characterId2": "TenSoon", "type": "", "bookId": "mistborn3"}, {"id": "TenSoon:Kelsier", "characterId1": "TenSoon", "characterId2": "Kelsier", "type": "", "bookId": "mistborn3"}, {"id": "TenSoon:OreSeur", "characterId1": "TenSoon", "characterId2": "OreSeur", "type": "", "bookId": "mistborn3"}, {"id": "Kelsier:OreSeur", "characterId1": "Kelsier", "characterId2": "OreSeur", "type": "", "bookId": "mistborn3"}, {"id": "TenSoon:Kelsier", "characterId1": "TenSoon", "characterId2": "Kelsier", "type": "", "bookId": "mistborn3"}, {"id": "Jaston:Wellen", "characterId1": "Jaston", "characterId2": "Wellen", "type": "", "bookId": "mistborn3"}, {"id": "Jaston:Skiff", "characterId1": "Jaston", "characterId2": "Skiff", "type": "", "bookId": "mistborn3"}, {"id": "Wellen:Skiff", "characterId1": "Wellen", "characterId2": "Skiff", "type": "", "bookId": "mistborn3"}, {"id": "Quellion:Beldre", "characterId1": "Quellion", "characterId2": "Beldre", "type": "", "bookId": "mistborn3"}, {"id": "Hammond:Vin", "characterId1": "Hammond", "characterId2": "Vin", "type": "", "bookId": "mistborn3"}, {"id": "Hammond:Edgard_Ladrian", "characterId1": "Hammond", "characterId2": "Edgard_Ladrian", "type": "", "bookId": "mistborn3"}, {"id": "Hammond:Sazed", "characterId1": "Hammond", "characterId2": "Sazed", "type": "", "bookId": "mistborn3"}, {"id": "Vin:Edgard_Ladrian", "characterId1": "Vin", "characterId2": "Edgard_Ladrian", "type": "", "bookId": "mistborn3"}, {"id": "Vin:Sazed", "characterId1": "Vin", "characterId2": "Sazed", "type": "", "bookId": "mistborn3"}, {"id": "Edgard_Ladrian:Sazed", "characterId1": "Edgard_Ladrian", "characterId2": "Sazed", "type": "", "bookId": "mistborn3"}, {"id": "Quellion:Edgard_Ladrian", "characterId1": "Quellion", "characterId2": "Edgard_Ladrian", "type": "", "bookId": "mistborn3"}, {"id": "Quellion:Spook", "characterId1": "Quellion", "characterId2": "Spook", "type": "", "bookId": "mistborn3"}, {"id": "Edgard_Ladrian:Spook", "characterId1": "Edgard_Ladrian", "characterId2": "Spook", "type": "", "bookId": "mistborn3"}, {"id": "Edgard_Ladrian:Spook", "characterId1": "Edgard_Ladrian", "characterId2": "Spook", "type": "", "bookId": "mistborn3"}, {"id": "Edgard_Ladrian:Goradel", "characterId1": "Edgard_Ladrian", "characterId2": "Goradel", "type": "", "bookId": "mistborn3"}, {"id": "Spook:Goradel", "characterId1": "Spook", "characterId2": "Goradel", "type": "", "bookId": "mistborn3"}, {"id": "Sazed:Goradel", "characterId1": "Sazed", "characterId2": "Goradel", "type": "", "bookId": "mistborn3"}, {"id": "Sazed:Spook", "characterId1": "Sazed", "characterId2": "Spook", "type": "", "bookId": "mistborn3"}, {"id": "Sazed:Edgard_Ladrian", "characterId1": "Sazed", "characterId2": "Edgard_Ladrian", "type": "", "bookId": "mistborn3"}, {"id": "Goradel:Spook", "characterId1": "Goradel", "characterId2": "Spook", "type": "", "bookId": "mistborn3"}, {"id": "Goradel:Edgard_Ladrian", "characterId1": "Goradel", "characterId2": "Edgard_Ladrian", "type": "", "bookId": "mistborn3"}, {"id": "Spook:Edgard_Ladrian", "characterId1": "Spook", "characterId2": "Edgard_Ladrian", "type": "", "bookId": "mistborn3"}, {"id": "Durn:Edgard_Ladrian", "characterId1": "Durn", "characterId2": "Edgard_Ladrian", "type": "", "bookId": "mistborn3"}, {"id": "Sazed:Beldre", "characterId1": "Sazed", "characterId2": "Beldre", "type": "", "bookId": "mistborn3"}, {"id": "Quellion:Goradel", "characterId1": "Quellion", "characterId2": "Goradel", "type": "", "bookId": "mistborn3"}, {"id": "Quellion:Durn", "characterId1": "Quellion", "characterId2": "Durn", "type": "", "bookId": "mistborn3"}, {"id": "Quellion:Spook", "characterId1": "Quellion", "characterId2": "Spook", "type": "", "bookId": "mistborn3"}, {"id": "Durn:Spook", "characterId1": "Durn", "characterId2": "Spook", "type": "", "bookId": "mistborn3"}, {"id": "Kelsier:Beldre", "characterId1": "Kelsier", "characterId2": "Beldre", "type": "", "bookId": "mistborn3"}, {"id": "Quellion:Kelsier", "characterId1": "Quellion", "characterId2": "Kelsier", "type": "", "bookId": "mistborn3"}, {"id": "Quellion:Spook", "characterId1": "Quellion", "characterId2": "Spook", "type": "", "bookId": "mistborn3"}, {"id": "Kelsier:Spook", "characterId1": "Kelsier", "characterId2": "Spook", "type": "", "bookId": "mistborn3"}, {"id": "TenSoon:Edgard_Ladrian", "characterId1": "TenSoon", "characterId2": "Edgard_Ladrian", "type": "", "bookId": "mistborn3"}, {"id": "Sazed:Tindwyl_Ladrian", "characterId1": "Sazed", "characterId2": "Tindwyl_Ladrian", "type": "", "bookId": "mistborn3"}, {"id": "Kwaan:Alendi", "characterId1": "Kwaan", "characterId2": "Alendi", "type": "", "bookId": "mistborn3"}, {"id": "Ati:Edgard_Ladrian", "characterId1": "Ati", "characterId2": "Edgard_Ladrian", "type": "", "bookId": "mistborn3"}, {"id": "Kwaan:Ati", "characterId1": "Kwaan", "characterId2": "Ati", "type": "", "bookId": "mistborn3"}, {"id": "Kwaan:Edgard_Ladrian", "characterId1": "Kwaan", "characterId2": "Edgard_Ladrian", "type": "", "bookId": "mistborn3"}, {"id": "Ati:Edgard_Ladrian", "characterId1": "Ati", "characterId2": "Edgard_Ladrian", "type": "", "bookId": "mistborn3"}, {"id": "Ati:Elend_Venture", "characterId1": "Ati", "characterId2": "Elend_Venture", "type": "", "bookId": "mistborn3"}, {"id": "Edgard_Ladrian:Beldre", "characterId1": "Edgard_Ladrian", "characterId2": "Beldre", "type": "", "bookId": "mistborn3"}, {"id": "Vin:Goradel", "characterId1": "Vin", "characterId2": "Goradel", "type": "", "bookId": "mistborn3"}, {"id": "Elend_Venture:Marsh", "characterId1": "Elend_Venture", "characterId2": "Marsh", "type": "", "bookId": "mistborn3"}, {"id": "Sazed:TenSoon", "characterId1": "Sazed", "characterId2": "TenSoon", "type": "", "bookId": "mistborn3"}, {"id": "Elend_Venture:Ati", "characterId1": "Elend_Venture", "characterId2": "Ati", "type": "", "bookId": "mistborn3"}, {"id": "Elend_Venture:Marsh", "characterId1": "Elend_Venture", "characterId2": "Marsh", "type": "", "bookId": "mistborn3"}, {"id": "Ati:Marsh", "characterId1": "Ati", "characterId2": "Marsh", "type": "", "bookId": "mistborn3"}, {"id": "Ati:Kelsier", "characterId1": "Ati", "characterId2": "Kelsier", "type": "", "bookId": "mistborn3"}, {"id": "Ati:Quellion", "characterId1": "Ati", "characterId2": "Quellion", "type": "", "bookId": "mistborn3"}, {"id": "Kelsier:Quellion", "characterId1": "Kelsier", "characterId2": "Quellion", "type": "", "bookId": "mistborn3"}, {"id": "Sazed:Haddek", "characterId1": "Sazed", "characterId2": "Haddek", "type": "", "bookId": "mistborn3"}, {"id": "Vin:Haddek", "characterId1": "Vin", "characterId2": "Haddek", "type": "", "bookId": "mistborn3"}, {"id": "Sazed:Edgard_Ladrian", "characterId1": "Sazed", "characterId2": "Edgard_Ladrian", "type": "", "bookId": "mistborn3"}, {"id": "Sazed:Elend_Venture", "characterId1": "Sazed", "characterId2": "Elend_Venture", "type": "", "bookId": "mistborn3"}, {"id": "Edgard_Ladrian:Elend_Venture", "characterId1": "Edgard_Ladrian", "characterId2": "Elend_Venture", "type": "", "bookId": "mistborn3"}, {"id": "Sazed:KanPaar", "characterId1": "Sazed", "characterId2": "KanPaar", "type": "", "bookId": "mistborn3"}, {"id": "Haddek:Rashek", "characterId1": "Haddek", "characterId2": "Rashek", "type": "", "bookId": "mistborn3"}, {"id": "Haddek:KanPaar", "characterId1": "Haddek", "characterId2": "KanPaar", "type": "", "bookId": "mistborn3"}, {"id": "Ati:Rashek", "characterId1": "Ati", "characterId2": "Rashek", "type": "", "bookId": "mistborn3"}, {"id": "Vin:Tindwyl_Ladrian", "characterId1": "Vin", "characterId2": "Tindwyl_Ladrian", "type": "", "bookId": "mistborn3"}, {"id": "KanPaar:MeLaan", "characterId1": "KanPaar", "characterId2": "MeLaan", "type": "", "bookId": "mistborn3"}, {"id": "FhorKood:TenSoon", "characterId1": "FhorKood", "characterId2": "TenSoon", "type": "", "bookId": "mistborn3"}, {"id": "MeLaan:TenSoon", "characterId1": "MeLaan", "characterId2": "TenSoon", "type": "", "bookId": "mistborn3"}, {"id": "MeLaan:FhorKood", "characterId1": "MeLaan", "characterId2": "FhorKood", "type": "", "bookId": "mistborn3"}, {"id": "TenSoon:FhorKood", "characterId1": "TenSoon", "characterId2": "FhorKood", "type": "", "bookId": "mistborn3"}, {"id": "Vin:Ati", "characterId1": "Vin", "characterId2": "Ati", "type": "", "bookId": "mistborn3"}, {"id": "Vin:KanPaar", "characterId1": "Vin", "characterId2": "KanPaar", "type": "", "bookId": "mistborn3"}, {"id": "Ati:KanPaar", "characterId1": "Ati", "characterId2": "KanPaar", "type": "", "bookId": "mistborn3"}, {"id": "Sazed:MeLaan", "characterId1": "Sazed", "characterId2": "MeLaan", "type": "", "bookId": "mistborn3"}, {"id": "Demoux:Aslydin", "characterId1": "Demoux", "characterId2": "Aslydin", "type": "", "bookId": "mistborn3"}, {"id": "Elend_Venture:Kelsier", "characterId1": "Elend_Venture", "characterId2": "Kelsier", "type": "", "bookId": "mistborn3"}, {"id": "Elend_Venture:Marsh", "characterId1": "Elend_Venture", "characterId2": "Marsh", "type": "", "bookId": "mistborn3"}, {"id": "Kelsier:Marsh", "characterId1": "Kelsier", "characterId2": "Marsh", "type": "", "bookId": "mistborn3"}, {"id": "Vin:Ati", "characterId1": "Vin", "characterId2": "Ati", "type": "", "bookId": "mistborn3"}, {"id": "Vin:Elend_Venture", "characterId1": "Vin", "characterId2": "Elend_Venture", "type": "", "bookId": "mistborn3"}, {"id": "Ati:Elend_Venture", "characterId1": "Ati", "characterId2": "Elend_Venture", "type": "", "bookId": "mistborn3"}, {"id": "Sazed:Vin", "characterId1": "Sazed", "characterId2": "Vin", "type": "", "bookId": "mistborn3"}, {"id": "Sazed:Kelsier", "characterId1": "Sazed", "characterId2": "Kelsier", "type": "", "bookId": "mistborn3"}, {"id": "Vin:Kelsier", "characterId1": "Vin", "characterId2": "Kelsier", "type": "", "bookId": "mistborn3"}, {"id": "Sazed:Vin", "characterId1": "Sazed", "characterId2": "Vin", "type": "", "bookId": "mistborn3"}, {"id": "Sazed:Mare", "characterId1": "Sazed", "characterId2": "Mare", "type": "", "bookId": "mistborn3"}, {"id": "Sazed:Kelsier", "characterId1": "Sazed", "characterId2": "Kelsier", "type": "", "bookId": "mistborn3"}, {"id": "Vin:Mare", "characterId1": "Vin", "characterId2": "Mare", "type": "", "bookId": "mistborn3"}, {"id": "Vin:Kelsier", "characterId1": "Vin", "characterId2": "Kelsier", "type": "", "bookId": "mistborn3"}, {"id": "Mare:Kelsier", "characterId1": "Mare", "characterId2": "Kelsier", "type": "", "bookId": "mistborn3"}, {"id": "Vin:Rashek", "characterId1": "Vin", "characterId2": "Rashek", "type": "", "bookId": "mistborn3"}, {"id": "Allrianne_Cett:Edgard_Ladrian", "characterId1": "Allrianne_Cett", "characterId2": "Edgard_Ladrian", "type": "", "bookId": "mistborn3"}, {"id": "Allrianne_Cett:Beldre", "characterId1": "Allrianne_Cett", "characterId2": "Beldre", "type": "", "bookId": "mistborn3"}, {"id": "Edgard_Ladrian:Beldre", "characterId1": "Edgard_Ladrian", "characterId2": "Beldre", "type": "", "bookId": "mistborn3"}, {"id": "Hammond:Spook", "characterId1": "Hammond", "characterId2": "Spook", "type": "", "bookId": "mistborn3"}, {"id": "Demoux:Spook", "characterId1": "Demoux", "characterId2": "Spook", "type": "", "bookId": "mistborn3"}, {"id": "Hammond:Edgard_Ladrian", "characterId1": "Hammond", "characterId2": "Edgard_Ladrian", "type": "", "bookId": "mistborn3"}, {"id": "Hammond:Spook", "characterId1": "Hammond", "characterId2": "Spook", "type": "", "bookId": "mistborn3"}, {"id": "Edgard_Ladrian:Spook", "characterId1": "Edgard_Ladrian", "characterId2": "Spook", "type": "", "bookId": "mistborn3"}]